{"stat.flyOneCm":5855,"stat.walkOneCm":12183,"stat.drop":1,"stat.useItem.minecraft.sticky_piston":1,"stat.jump":21,"stat.trappedChestTriggered":1,"stat.playOneMinute":37377,"stat.useItem.minecraft.lever":3,"achievement.openInventory":10,"stat.useItem.minecraft.stone":36,"stat.leaveGame":1,"stat.sneakTime":56,"stat.useItem.minecraft.piston":1,"stat.drop.prospecting.Ruby_Gem":1,"stat.useItem.minecraft.stone_brick_stairs":3,"stat.crouchOneCm":229,"stat.timeSinceDeath":37377,"stat.sprintOneCm":826,"achievement.exploreAllBiomes":{"value":0,"progress":["Plains"]}}